LICENSE.txt
README.md
setup.cfg
setup.py
ddql_optimal_execution/__init__.py
ddql_optimal_execution/_utils.py
ddql_optimal_execution.egg-info/PKG-INFO
ddql_optimal_execution.egg-info/SOURCES.txt
ddql_optimal_execution.egg-info/dependency_links.txt
ddql_optimal_execution.egg-info/requires.txt
ddql_optimal_execution.egg-info/top_level.txt
ddql_optimal_execution/agent/__init__.py
ddql_optimal_execution/agent/_agent.py
ddql_optimal_execution/agent/_ddql.py
ddql_optimal_execution/agent/_neural_net.py
ddql_optimal_execution/agent/_twap.py
ddql_optimal_execution/environnement/__init__.py
ddql_optimal_execution/environnement/_data_processing.py
ddql_optimal_execution/environnement/_env.py
ddql_optimal_execution/environnement/_exceptions.py
ddql_optimal_execution/environnement/_utils.py
ddql_optimal_execution/experience_replay/__init__.py
ddql_optimal_execution/experience_replay/_exceptions.py
ddql_optimal_execution/experience_replay/_experience_dict.py
ddql_optimal_execution/experience_replay/_experience_replay.py
ddql_optimal_execution/experience_replay/_warnings.py
ddql_optimal_execution/preprocessing/__init__.py
ddql_optimal_execution/preprocessing/_preprocessor.py
ddql_optimal_execution/state/__init__.py
ddql_optimal_execution/state/_state.py
ddql_optimal_execution/state/_state_array.py
ddql_optimal_execution/trainer/__init__.py
ddql_optimal_execution/trainer/_trainer.py
ddql_optimal_execution/trainer/_warnings.py
tests/test_MarketEnvironnement.py
tests/test_State.py
tests/test_experience_replay.py
tests/test_preprocessing.py
tests/tests_data_utils.py